{
  "template_name"                         : "fedora-34-x86_64",
  "template_os"                           : "fedora64Guest",
  "beakerhost"                            : "fedora34-64",
  "version"                               : "0.0.2",
  "iso_url"                               : "https://artifactory.delivery.puppetlabs.net/artifactory/generic/iso/Fedora-Server-dvd-x86_64-34-1.2.iso",
  "iso_checksum"                          : "cd2aefdbe1b5042865a39c49d32f5d21a9537c719aa87dde34d08ca06bc6681c",
  "iso_checksum_type"                     : "sha256",
  "vmware_vsphere_nocm_vmx_data_memsize"  : "4096",
  "vmware_vsphere_nocm_vmx_data_numvcpus" : "2",
  "floppy_files"                          : "../files/ks.cfg",
  "puppet_aio"                            : "http://yum.puppetlabs.com/puppet6/fedora/32/x86_64/puppet-agent-6.22.1-1.fc32.x86_64.rpm",
  "iso_name"                              : "Fedora-Server-dvd-x86_64-34-1.2.iso",
  "inject_http_seed_in_boot_command"      : "true",
  "boot_command"                          : "<tab> inst.text inst.ks=http://%s/ks.cfg <enter>",
  "http_directory"                        : "../files/"
}
